novowrap/__init__.py
novowrap/__main__.py
novowrap/assembly.py
novowrap/merge.py
novowrap/ui.py
novowrap/utils.py
novowrap/validate.py
novowrap-1.32.dist-info/LICENSE
novowrap-1.32.dist-info/METADATA
novowrap-1.32.dist-info/WHEEL
novowrap-1.32.dist-info/entry_points.txt
novowrap-1.32.dist-info/top_level.txt
novowrap-1.32.dist-info/RECORD
