Metadata-Version: 2.1
Name: novowrap
Version: 1.32
Summary: Assembly Plastid Genome
Author-email: Ping Wu <wpwupingwp@outlook.com>
License: GNU AGPL v3
Project-URL: Homepage, https://github.com/wpwupingwp/novowrap
Classifier: Development Status :: 5 - Production/Stable
Classifier: Intended Audience :: Science/Research
Classifier: License :: OSI Approved :: GNU Affero General Public License v3
Classifier: Operating System :: OS Independent
Classifier: Programming Language :: Python :: 3
Classifier: Topic :: Scientific/Engineering :: Bio-Informatics
Requires-Python: >=3.7
License-File: LICENSE
Requires-Dist: biopython >=1.77
Requires-Dist: coloredlogs >=10.0
Requires-Dist: matplotlib >=3.2.0
Requires-Dist: numpy >=1.19.1
Requires-Dist: pip >=18.0
Requires-Dist: graphviz >=0.13
